borax/__init__.py
borax/choices.py
borax/constants.py
borax/devtools.py
borax/htmls.py
borax/numbers.py
borax/strings.py
borax/system.py
borax/utils.py
borax/calendars/__init__.py
borax/calendars/birthday.py
borax/calendars/data_parser.py
borax/calendars/datepicker.py
borax/calendars/festivals2.py
borax/calendars/lunardate.py
borax/calendars/ui.py
borax/calendars/utils.py
borax/calendars/dataset/FestivalData.csv
borax/calendars/dataset/__init__.py
borax/calendars/dataset/festivals_ext1.csv
borax/capp/__init__.py
borax/capp/__main__.py
borax/capp/borax_calendar_app.py
borax/capp/festival_creator.py
borax/counters/__init__.py
borax/counters/daily.py
borax/counters/serial_pool.py
borax/datasets/__init__.py
borax/datasets/fetch.py
borax/datasets/join_.py
borax/patterns/__init__.py
borax/patterns/lazy.py
borax/patterns/proxy.py
borax/patterns/singleton.py
borax/serialize/__init__.py
borax/serialize/cjson.py
borax/structures/__init__.py
borax/structures/dictionary.py
borax/structures/percentage.py
borax/structures/tree.py
borax/ui/__init__.py
borax/ui/aiotk.py
borax/ui/widgets.py
borax-4.1.3.dist-info/licenses/LICENSE
borax-4.1.3.dist-info/METADATA
borax-4.1.3.dist-info/WHEEL
borax-4.1.3.dist-info/top_level.txt
borax-4.1.3.dist-info/RECORD
