Metadata-Version: 2.4
Name: borax
Version: 4.1.3
Summary: A tool collections.(Chinese-Lunar-Calendars/Python-Patterns)
Author: kinegratii
Author-email: kinegratii <zhenwei.yan@hotmail.com>
License: MIT License
Project-URL: Homepage, https://github.com/kinegratii/borax
Project-URL: Documentation, https://borax.readthedocs.io/zh_CN/latest/
Project-URL: Repository, https://github.com/kinegratii/borax
Keywords: chinese lunar calendar,python tool
Classifier: Development Status :: 5 - Production/Stable
Classifier: Programming Language :: Python :: 3
Classifier: Programming Language :: Python :: 3.9
Classifier: Programming Language :: Python :: 3.10
Classifier: Programming Language :: Python :: 3.11
Classifier: Programming Language :: Python :: 3.12
Classifier: Programming Language :: Python :: 3.13
Classifier: Programming Language :: Python :: 3 :: Only
Classifier: Intended Audience :: Developers
Classifier: License :: OSI Approved :: MIT License
Classifier: Topic :: Software Development :: Libraries
Classifier: Topic :: Utilities
Classifier: Operating System :: OS Independent
Requires-Python: >=3.9
License-File: LICENSE
Dynamic: author
Dynamic: license-file
Dynamic: requires-python
